{
    "sourceFile": "packages/react/index.ts",
    "activeCommit": 0,
    "commits": [
        {
            "activePatchIndex": 1,
            "patches": [
                {
                    "date": 1719313854585,
                    "content": "Index: \n===================================================================\n--- \n+++ \n"
                },
                {
                    "date": 1719314938020,
                    "content": "Index: \n===================================================================\n--- \n+++ \n@@ -1,1 +1,1 @@\n-export { default as jsx } from \"./jsx_runtime\";\n+export { default as jsx } from \"./jsx-runtime\";\n"
                }
            ],
            "date": 1719313854585,
            "name": "Commit-0",
            "content": "export { default as jsx } from \"./jsx_runtime\";\n"
        }
    ]
}